github_release_update_checker/__init__.py
github_release_update_checker/main.py
github_release_update_checker-1.0.4.dist-info/LICENSE
github_release_update_checker-1.0.4.dist-info/METADATA
github_release_update_checker-1.0.4.dist-info/WHEEL
github_release_update_checker-1.0.4.dist-info/top_level.txt
github_release_update_checker-1.0.4.dist-info/RECORD
