Metadata-Version: 2.1
Name: github-release-update-checker
Version: 1.0.4
Summary: A simple GUI-based update notifier in Python
Home-page: https://github.com/1325ok/Python-Github-Release-Update-Checker
Author: 1325OK
Author-email: 1325ok.help@gmail.com
Keywords: github,release,update,checker,tkinter,gui
Classifier: Programming Language :: Python :: 3
Classifier: License :: OSI Approved :: MIT License
Classifier: Operating System :: OS Independent
Requires-Python: >=3.6
License-File: LICENSE
Requires-Dist: requests
